odoo/addons/sale_elaboration_margin/README.rst
odoo/addons/sale_elaboration_margin/__init__.py
odoo/addons/sale_elaboration_margin/__manifest__.py
odoo/addons/sale_elaboration_margin/i18n/es.po
odoo/addons/sale_elaboration_margin/i18n/sale_elaboration_margin.pot
odoo/addons/sale_elaboration_margin/models/__init__.py
odoo/addons/sale_elaboration_margin/models/sale_order.py
odoo/addons/sale_elaboration_margin/readme/CONTRIBUTORS.rst
odoo/addons/sale_elaboration_margin/readme/DESCRIPTION.rst
odoo/addons/sale_elaboration_margin/readme/USAGE.rst
odoo/addons/sale_elaboration_margin/static/description/icon.png
odoo/addons/sale_elaboration_margin/static/description/index.html
odoo/addons/sale_elaboration_margin/views/sale_order_views.xml
odoo_addon_sale_elaboration_margin-15.0.2.0.0.1.dist-info/METADATA
odoo_addon_sale_elaboration_margin-15.0.2.0.0.1.dist-info/WHEEL
odoo_addon_sale_elaboration_margin-15.0.2.0.0.1.dist-info/top_level.txt
odoo_addon_sale_elaboration_margin-15.0.2.0.0.1.dist-info/RECORD
